{
  "unversionedId": "development/installation",
  "id": "development/installation",
  "isDocsHomePage": false,
  "title": "Installation",
  "description": "",
  "source": "@site/docs/development/installation copy.md",
  "sourceDirName": "development",
  "slug": "/development/installation",
  "permalink": "/development/installation",
  "editUrl": "https://github.com/erxes/erxes/edit/erxes-docs-blog/docs/docs/development/installation copy.md",
  "version": "current",
  "lastUpdatedBy": "Author",
  "lastUpdatedAt": 1539502055,
  "formattedLastUpdatedAt": "10/14/2018",
  "sidebar_label": "Installation",
  "frontMatter": {
    "id": "installation",
    "title": "Installation",
    "sidebar_label": "Installation"
  },
  "sidebar": "docs",
  "previous": {
    "title": "Integration",
    "permalink": "/contribute/integration"
  },
  "next": {
    "title": "Overview",
    "permalink": "/contribute/overview"
  }
}