{
  "unversionedId": "ubuntu/prerequisites",
  "id": "ubuntu/prerequisites",
  "isDocsHomePage": false,
  "title": "Prerequisites",
  "description": "",
  "source": "@site/docs/ubuntu/prerequisites.md",
  "sourceDirName": "ubuntu",
  "slug": "/ubuntu/prerequisites",
  "permalink": "/ubuntu/prerequisites",
  "editUrl": "https://github.com/erxes/erxes/edit/erxes-docs-blog/docs/docs/ubuntu/prerequisites.md",
  "version": "current",
  "lastUpdatedBy": "Author",
  "lastUpdatedAt": 1539502055,
  "formattedLastUpdatedAt": "10/14/2018",
  "sidebar_label": "Prerequisites",
  "frontMatter": {
    "id": "prerequisites",
    "title": "Prerequisites",
    "sidebar_label": "Prerequisites"
  }
}