{
  "unversionedId": "developer/push-notifications",
  "id": "developer/push-notifications",
  "isDocsHomePage": false,
  "title": "Push notifications",
  "description": "Push Notifications are an important feature to retain and re-engage users and monetize on their attention. We use Firebase's cloud messaging feature as a push notification service. Let's get started with following steps.",
  "source": "@site/docs/developer/push-notifications.md",
  "sourceDirName": "developer",
  "slug": "/developer/push-notifications",
  "permalink": "/developer/push-notifications",
  "editUrl": "https://github.com/erxes/erxes/edit/develop/docs/docs/developer/push-notifications.md",
  "version": "current",
  "lastUpdatedBy": "Author",
  "lastUpdatedAt": 1539502055,
  "formattedLastUpdatedAt": "10/14/2018",
  "sidebar_label": "Push notifications",
  "frontMatter": {
    "id": "push-notifications",
    "title": "Push notifications",
    "sidebar_label": "Push notifications"
  },
  "sidebar": "docs",
  "previous": {
    "title": "iOS SDK",
    "permalink": "/developer/ios-sdk"
  },
  "next": {
    "title": "Script installation",
    "permalink": "/user/script-install"
  }
}